reader/__init__.py
reader/__main__.py
reader/config.toml
reader/feed.py
reader/viewer.py
backend_setuptool-1.4.0.dist-info/LICENSE
backend_setuptool-1.4.0.dist-info/METADATA
backend_setuptool-1.4.0.dist-info/WHEEL
backend_setuptool-1.4.0.dist-info/entry_points.txt
backend_setuptool-1.4.0.dist-info/top_level.txt
backend_setuptool-1.4.0.dist-info/RECORD
